{".class":"MypyFile","_fullname":"sqlalchemy.event.base","future_import_flags":[],"is_partial_stub_package":false,"is_stub":true,"names":{".class":"SymbolTable","Any":{".class":"SymbolTableNode","cross_ref":"typing.Any","kind":"Gdef","module_hidden":true,"module_public":false},"Events":{".class":"SymbolTableNode","kind":"Gdef","node":{".class":"TypeInfo","_promote":[],"abstract_attributes":[],"alt_promote":null,"bases":["builtins.object"],"dataclass_transform_spec":null,"declared_metaclass":"sqlalchemy.event.base._EventMeta","defn":{".class":"ClassDef","fullname":"sqlalchemy.event.base.Events","name":"Events","type_vars":[]},"deletable_attributes":[],"deprecated":null,"flags":[],"fullname":"sqlalchemy.event.base.Events","has_param_spec_type":false,"metaclass_type":"sqlalchemy.event.base._EventMeta","metadata":{},"module_name":"sqlalchemy.event.base","mro":["sqlalchemy.event.base.Events","builtins.object"],"names":{".class":"SymbolTable"},"self_type":{".class":"TypeVarType","default":{".class":"AnyType","missing_import_name":null,"source_any":null,"type_of_any":4},"fullname":"sqlalchemy.event.base.Events.Self","id":0,"name":"Self","namespace":"","upper_bound":"sqlalchemy.event.base.Events","values":[],"variance":0},"slots":null,"tuple_type":null,"type_vars":[],"typeddict_type":null}},"Optional":{".class":"SymbolTableNode","cross_ref":"typing.Optional","kind":"Gdef","module_hidden":true,"module_public":false},"_EventMeta":{".class":"SymbolTableNode","kind":"Gdef","node":{".class":"TypeInfo","_promote":[],"abstract_attributes":[],"alt_promote":null,"bases":["builtins.type"],"dataclass_transform_spec":null,"declared_metaclass":null,"defn":{".class":"ClassDef","fullname":"sqlalchemy.event.base._EventMeta","name":"_EventMeta","type_vars":[]},"deletable_attributes":[],"deprecated":null,"flags":[],"fullname":"sqlalchemy.event.base._EventMeta","has_param_spec_type":false,"metaclass_type":null,"metadata":{},"module_name":"sqlalchemy.event.base","mro":["sqlalchemy.event.base._EventMeta","builtins.type","builtins.object"],"names":{".class":"SymbolTable","__init__":{".class":"SymbolTableNode","kind":"Mdef","node":{".class":"FuncDef","abstract_status":0,"arg_kinds":[0,0,0,0],"arg_names":["cls","classname","bases","dict_"],"dataclass_transform_spec":null,"deprecated":null,"flags":["is_trivial_self"],"fullname":"sqlalchemy.event.base._EventMeta.__init__","name":"__init__","original_first_arg":"cls","type":{".class":"CallableType","arg_kinds":[0,0,0,0],"arg_names":["cls","classname","bases","dict_"],"arg_types":["sqlalchemy.event.base._EventMeta",{".class":"AnyType","missing_import_name":null,"source_any":null,"type_of_any":1},{".class":"AnyType","missing_import_name":null,"source_any":null,"type_of_any":1},{".class":"AnyType","missing_import_name":null,"source_any":null,"type_of_any":1}],"fallback":"builtins.function","from_concatenate":false,"implicit":false,"imprecise_arg_kinds":false,"is_bound":false,"is_ellipsis_args":false,"name":"__init__ of _EventMeta","ret_type":{".class":"NoneType"},"type_guard":null,"type_is":null,"unpack_kwargs":false,"variables":[]}}}},"self_type":{".class":"TypeVarType","default":{".class":"AnyType","missing_import_name":null,"source_any":null,"type_of_any":4},"fullname":"sqlalchemy.event.base._EventMeta.Self","id":0,"name":"Self","namespace":"","upper_bound":"sqlalchemy.event.base._EventMeta","values":[],"variance":0},"slots":null,"tuple_type":null,"type_vars":[],"typeddict_type":null}},"__annotations__":{".class":"SymbolTableNode","kind":"Gdef","node":{".class":"Var","flags":["is_ready"],"fullname":"sqlalchemy.event.base.__annotations__","name":"__annotations__","setter_type":null,"type":{".class":"Instance","args":["builtins.str",{".class":"AnyType","missing_import_name":null,"source_any":null,"type_of_any":6}],"extra_attrs":null,"type_ref":"builtins.dict"}}},"__doc__":{".class":"SymbolTableNode","kind":"Gdef","node":{".class":"Var","flags":["is_ready"],"fullname":"sqlalchemy.event.base.__doc__","name":"__doc__","setter_type":null,"type":"builtins.str"}},"__file__":{".class":"SymbolTableNode","kind":"Gdef","node":{".class":"Var","flags":["is_ready"],"fullname":"sqlalchemy.event.base.__file__","name":"__file__","setter_type":null,"type":"builtins.str"}},"__name__":{".class":"SymbolTableNode","kind":"Gdef","node":{".class":"Var","flags":["is_ready"],"fullname":"sqlalchemy.event.base.__name__","name":"__name__","setter_type":null,"type":"builtins.str"}},"__package__":{".class":"SymbolTableNode","kind":"Gdef","node":{".class":"Var","flags":["is_ready"],"fullname":"sqlalchemy.event.base.__package__","name":"__package__","setter_type":null,"type":"builtins.str"}},"__spec__":{".class":"SymbolTableNode","kind":"Gdef","node":{".class":"Var","flags":["is_ready"],"fullname":"sqlalchemy.event.base.__spec__","name":"__spec__","setter_type":null,"type":"_frozen_importlib.ModuleSpec"}},"dispatcher":{".class":"SymbolTableNode","kind":"Gdef","node":{".class":"TypeInfo","_promote":[],"abstract_attributes":[],"alt_promote":null,"bases":["builtins.object"],"dataclass_transform_spec":null,"declared_metaclass":null,"defn":{".class":"ClassDef","fullname":"sqlalchemy.event.base.dispatcher","name":"dispatcher","type_vars":[]},"deletable_attributes":[],"deprecated":null,"flags":[],"fullname":"sqlalchemy.event.base.dispatcher","has_param_spec_type":false,"metaclass_type":null,"metadata":{},"module_name":"sqlalchemy.event.base","mro":["sqlalchemy.event.base.dispatcher","builtins.object"],"names":{".class":"SymbolTable","__get__":{".class":"SymbolTableNode","kind":"Mdef","node":{".class":"FuncDef","abstract_status":0,"arg_kinds":[0,0,0],"arg_names":["self","obj","cls"],"dataclass_transform_spec":null,"deprecated":null,"flags":[],"fullname":"sqlalchemy.event.base.dispatcher.__get__","name":"__get__","original_first_arg":"self","type":null}},"__init__":{".class":"SymbolTableNode","kind":"Mdef","node":{".class":"FuncDef","abstract_status":0,"arg_kinds":[0,0],"arg_names":["self","events"],"dataclass_transform_spec":null,"deprecated":null,"flags":["is_trivial_self"],"fullname":"sqlalchemy.event.base.dispatcher.__init__","name":"__init__","original_first_arg":"self","type":{".class":"CallableType","arg_kinds":[0,0],"arg_names":["self","events"],"arg_types":["sqlalchemy.event.base.dispatcher",{".class":"AnyType","missing_import_name":null,"source_any":null,"type_of_any":1}],"fallback":"builtins.function","from_concatenate":false,"implicit":false,"imprecise_arg_kinds":false,"is_bound":false,"is_ellipsis_args":false,"name":"__init__ of dispatcher","ret_type":{".class":"NoneType"},"type_guard":null,"type_is":null,"unpack_kwargs":false,"variables":[]}}},"dispatch_cls":{".class":"SymbolTableNode","kind":"Mdef","node":{".class":"Var","flags":["is_initialized_in_class","is_ready","has_explicit_value"],"fullname":"sqlalchemy.event.base.dispatcher.dispatch_cls","name":"dispatch_cls","setter_type":null,"type":{".class":"AnyType","missing_import_name":null,"source_any":null,"type_of_any":2}}},"events":{".class":"SymbolTableNode","kind":"Mdef","node":{".class":"Var","flags":["is_initialized_in_class","is_ready","has_explicit_value"],"fullname":"sqlalchemy.event.base.dispatcher.events","name":"events","setter_type":null,"type":{".class":"AnyType","missing_import_name":null,"source_any":null,"type_of_any":2}}}},"self_type":{".class":"TypeVarType","default":{".class":"AnyType","missing_import_name":null,"source_any":null,"type_of_any":4},"fullname":"sqlalchemy.event.base.dispatcher.Self","id":0,"name":"Self","namespace":"","upper_bound":"sqlalchemy.event.base.dispatcher","values":[],"variance":0},"slots":null,"tuple_type":null,"type_vars":[],"typeddict_type":null}}},"path":"/Users/davidtessier/Documents/GitHub/autothreatai/.venv/lib/python3.14/site-packages/sqlalchemy-stubs/event/base.pyi"}